adblockparser/__init__.py
adblockparser/parser.py
adblockparser/utils.py
adblockparser-0.7.dist-info/DESCRIPTION.rst
adblockparser-0.7.dist-info/METADATA
adblockparser-0.7.dist-info/RECORD
adblockparser-0.7.dist-info/WHEEL
adblockparser-0.7.dist-info/metadata.json
adblockparser-0.7.dist-info/pbr.json
adblockparser-0.7.dist-info/top_level.txt
