Metadata-Version: 1.1
Name: adblockparser
Version: 0.7
Summary: Parser for Adblock Plus rules
Home-page: https://github.com/scrapinghub/adblockparser
Author: Mikhail Korobov
Author-email: kmike84@gmail.com
License: MIT
Keywords: adblock easylist
Platform: UNKNOWN
Classifier: Development Status :: 4 - Beta
Classifier: Intended Audience :: Developers
Classifier: License :: OSI Approved :: MIT License
Classifier: Programming Language :: Python :: 2
Classifier: Programming Language :: Python :: 2.7
Classifier: Programming Language :: Python :: 3
Classifier: Programming Language :: Python :: 3.3
Classifier: Programming Language :: Python :: 3.4
Classifier: Programming Language :: Python :: 3.5
